deftlariat/__init__.py
deftlariat/core.py
deftlariat/py.typed
deftlariat/scripts/__init__.py
deftlariat/scripts/cli.py
pydeftlariats-1.2.11.dist-info/licenses/AUTHORS.rst
pydeftlariats-1.2.11.dist-info/licenses/LICENSE
pydeftlariats-1.2.11.dist-info/METADATA
pydeftlariats-1.2.11.dist-info/WHEEL
pydeftlariats-1.2.11.dist-info/entry_points.txt
pydeftlariats-1.2.11.dist-info/top_level.txt
pydeftlariats-1.2.11.dist-info/RECORD
