Metadata-Version: 2.4
Name: PyDeftLariats
Version: 1.2.11
Summary: Using PyHamcrest to build a collection of data filters.
Home-page: https://github.com/mcmasty/PyDeftLariats
Author: Tyler McMaster
Author-email: mcmasty@yahoo.com
License: GNU General Public License v3
Keywords: hamcrest matchers data filters
Classifier: Development Status :: 2 - Pre-Alpha
Classifier: Intended Audience :: Developers
Classifier: License :: OSI Approved :: GNU General Public License v3 (GPLv3)
Classifier: Natural Language :: English
Classifier: Programming Language :: Python :: 3
Classifier: Programming Language :: Python :: 3.7
Classifier: Programming Language :: Python :: 3.8
Classifier: Programming Language :: Python :: 3.9
Provides: deftlariat
Requires-Python: >=3.11
License-File: LICENSE
License-File: AUTHORS.rst
Requires-Dist: click>=8.1.8
Requires-Dist: alabaster>=1.0.0
Requires-Dist: PyHamcrest~=2.0.4
Dynamic: author
Dynamic: author-email
Dynamic: classifier
Dynamic: description
Dynamic: description-content-type
Dynamic: home-page
Dynamic: keywords
Dynamic: license
Dynamic: license-file
Dynamic: provides
Dynamic: requires-dist
Dynamic: requires-python
Dynamic: summary
